numato_cli/__init__.py
numato_cli/__main__.py
numato_cli/test_numato_cli.py
numato_cli-0.1.0.dist-info/entry_points.txt
numato_cli-0.1.0.dist-info/LICENSE
numato_cli-0.1.0.dist-info/WHEEL
numato_cli-0.1.0.dist-info/METADATA
numato_cli-0.1.0.dist-info/RECORD
