Metadata-Version: 2.1
Name: numato-cli
Version: 0.1.0
Summary: Command-line interface for Numato GPIO expanders
License: MIT
Author: Henning Claßen
Author-email: code@clssn.de
Requires-Python: >=3.8,<4.0
Classifier: License :: OSI Approved :: MIT License
Classifier: Programming Language :: Python :: 3
Classifier: Programming Language :: Python :: 3.10
Classifier: Programming Language :: Python :: 3.8
Classifier: Programming Language :: Python :: 3.9
Requires-Dist: colorama (>=0.4.4,<0.5.0)
Requires-Dist: numato-gpio (>=0.10.0,<0.11.0)
Requires-Dist: shellingham (>=1.4.0,<2.0.0)
Requires-Dist: typer[all] (>=0.4.0,<0.5.0)
